llmpeg/__init__.py
llmpeg/cli.py
llmpeg/config.py
llmpeg/conversation.py
llmpeg/llm.py
llmpeg/setup.py
llmpeg-0.1.2.dist-info/METADATA
llmpeg-0.1.2.dist-info/WHEEL
llmpeg-0.1.2.dist-info/entry_points.txt
llmpeg-0.1.2.dist-info/licenses/LICENSE
llmpeg-0.1.2.dist-info/RECORD
