Metadata-Version: 2.4
Name: llmpeg
Version: 0.1.2
Summary: LLM-powered FFmpeg command assistant
Project-URL: Homepage, https://github.com/imortaltatsu/llmpeg
Project-URL: Repository, https://github.com/imortaltatsu/llmpeg
Project-URL: Issues, https://github.com/imortaltatsu/llmpeg/issues
Author: imortaltatsu
License: MIT
License-File: LICENSE
Keywords: ai,audio,compression,conversion,ffmpeg,llm,video
Classifier: Development Status :: 4 - Beta
Classifier: Intended Audience :: Developers
Classifier: License :: OSI Approved :: MIT License
Classifier: Programming Language :: Python :: 3
Classifier: Programming Language :: Python :: 3.12
Classifier: Programming Language :: Python :: 3.13
Classifier: Topic :: Multimedia :: Sound/Audio
Classifier: Topic :: Multimedia :: Video
Classifier: Topic :: Utilities
Requires-Python: >=3.12
Requires-Dist: openai>=1.0.0
Requires-Dist: pydantic>=2.12.4
Requires-Dist: rich>=14.2.0
Requires-Dist: typer>=0.20.0
